{
  "aartis": [
    {
      "id": "a1",
      "category": "विष्णु",
      "title": "ॐ जय जगदीश हरे",
      "lyrics": "ॐ जय जगदीश हरे, स्वामी जय जगदीश हरे..."
    },
    {
      "id": "a2",
      "category": "गणेश",
      "title": "जय गणेश देवा",
      "lyrics": "जय गणेश जय गणेश जय गणेश देवा..."
    },
    {
      "id": "a3",
      "category": "शिव",
      "title": "ॐ जय शिव ओंकारा",
      "lyrics": "ॐ जय शिव ओंकारा..."
    },
    {
      "id": "a4",
      "category": "हनुमान",
      "title": "आरती कीजै हनुमान लला की",
      "lyrics": "आरती कीजै हनुमान लला की..."
    },
    {
      "id": "a5",
      "category": "दुर्गा",
      "title": "जय अम्बे गौरी",
      "lyrics": "जय अम्बे गौरी, मैया जय श्यामा गौरी..."
    },
    {
      "id": "a6",
      "category": "कृष्ण",
      "title": "आरती कुंजबिहारी की",
      "lyrics": "आरती कुंजबिहारी की, श्री गिरधर कृष्ण मुरारी की..."
    },
    {
      "id": "a7",
      "category": "राम",
      "title": "आरती श्री रामचन्द्र जी की",
      "lyrics": "आरती श्री रामचन्द्र जी की..."
    },
    {
      "id": "a8",
      "category": "लक्ष्मी",
      "title": "ॐ जय लक्ष्मी माता",
      "lyrics": "ॐ जय लक्ष्मी माता..."
    },
    {
      "id": "a9",
      "category": "सरस्वती",
      "title": "जय सरस्वती माता",
      "lyrics": "जय सरस्वती माता..."
    },
    {
      "id": "a10",
      "category": "साई",
      "title": "आरती सांई बाबा",
      "lyrics": "आरती सांई बाबा, सौख्यदाता आरती..."
    },
    {
      "id": "a11",
      "category": "झूलेलाल",
      "title": "आरती #11",
      "lyrics": "झूलेलाल आरती #11 के पद..."
    },
    {
      "id": "a12",
      "category": "शिव",
      "title": "आरती #12",
      "lyrics": "शिव आरती #12 के पद..."
    },
    {
      "id": "a13",
      "category": "कृष्ण",
      "title": "आरती #13",
      "lyrics": "कृष्ण आरती #13 के पद..."
    },
    {
      "id": "a14",
      "category": "राम",
      "title": "आरती #14",
      "lyrics": "राम आरती #14 के पद..."
    },
    {
      "id": "a15",
      "category": "हनुमान",
      "title": "आरती #15",
      "lyrics": "हनुमान आरती #15 के पद..."
    },
    {
      "id": "a16",
      "category": "दुर्गा",
      "title": "आरती #16",
      "lyrics": "दुर्गा आरती #16 के पद..."
    },
    {
      "id": "a17",
      "category": "लक्ष्मी",
      "title": "आरती #17",
      "lyrics": "लक्ष्मी आरती #17 के पद..."
    },
    {
      "id": "a18",
      "category": "सरस्वती",
      "title": "आरती #18",
      "lyrics": "सरस्वती आरती #18 के पद..."
    },
    {
      "id": "a19",
      "category": "साई",
      "title": "आरती #19",
      "lyrics": "साई आरती #19 के पद..."
    },
    {
      "id": "a20",
      "category": "गायत्री",
      "title": "आरती #20",
      "lyrics": "गायत्री आरती #20 के पद..."
    },
    {
      "id": "a21",
      "category": "खाटू श्याम",
      "title": "आरती #21",
      "lyrics": "खाटू श्याम आरती #21 के पद..."
    },
    {
      "id": "a22",
      "category": "भैरव",
      "title": "आरती #22",
      "lyrics": "भैरव आरती #22 के पद..."
    },
    {
      "id": "a23",
      "category": "झूलेलाल",
      "title": "आरती #23",
      "lyrics": "झूलेलाल आरती #23 के पद..."
    },
    {
      "id": "a24",
      "category": "शिव",
      "title": "आरती #24",
      "lyrics": "शिव आरती #24 के पद..."
    },
    {
      "id": "a25",
      "category": "कृष्ण",
      "title": "आरती #25",
      "lyrics": "कृष्ण आरती #25 के पद..."
    },
    {
      "id": "a26",
      "category": "राम",
      "title": "आरती #26",
      "lyrics": "राम आरती #26 के पद..."
    },
    {
      "id": "a27",
      "category": "हनुमान",
      "title": "आरती #27",
      "lyrics": "हनुमान आरती #27 के पद..."
    },
    {
      "id": "a28",
      "category": "दुर्गा",
      "title": "आरती #28",
      "lyrics": "दुर्गा आरती #28 के पद..."
    },
    {
      "id": "a29",
      "category": "लक्ष्मी",
      "title": "आरती #29",
      "lyrics": "लक्ष्मी आरती #29 के पद..."
    },
    {
      "id": "a30",
      "category": "सरस्वती",
      "title": "आरती #30",
      "lyrics": "सरस्वती आरती #30 के पद..."
    },
    {
      "id": "a31",
      "category": "साई",
      "title": "आरती #31",
      "lyrics": "साई आरती #31 के पद..."
    },
    {
      "id": "a32",
      "category": "गायत्री",
      "title": "आरती #32",
      "lyrics": "गायत्री आरती #32 के पद..."
    },
    {
      "id": "a33",
      "category": "खाटू श्याम",
      "title": "आरती #33",
      "lyrics": "खाटू श्याम आरती #33 के पद..."
    },
    {
      "id": "a34",
      "category": "भैरव",
      "title": "आरती #34",
      "lyrics": "भैरव आरती #34 के पद..."
    },
    {
      "id": "a35",
      "category": "झूलेलाल",
      "title": "आरती #35",
      "lyrics": "झूलेलाल आरती #35 के पद..."
    },
    {
      "id": "a36",
      "category": "शिव",
      "title": "आरती #36",
      "lyrics": "शिव आरती #36 के पद..."
    },
    {
      "id": "a37",
      "category": "कृष्ण",
      "title": "आरती #37",
      "lyrics": "कृष्ण आरती #37 के पद..."
    },
    {
      "id": "a38",
      "category": "राम",
      "title": "आरती #38",
      "lyrics": "राम आरती #38 के पद..."
    },
    {
      "id": "a39",
      "category": "हनुमान",
      "title": "आरती #39",
      "lyrics": "हनुमान आरती #39 के पद..."
    },
    {
      "id": "a40",
      "category": "दुर्गा",
      "title": "आरती #40",
      "lyrics": "दुर्गा आरती #40 के पद..."
    },
    {
      "id": "a41",
      "category": "लक्ष्मी",
      "title": "आरती #41",
      "lyrics": "लक्ष्मी आरती #41 के पद..."
    },
    {
      "id": "a42",
      "category": "सरस्वती",
      "title": "आरती #42",
      "lyrics": "सरस्वती आरती #42 के पद..."
    },
    {
      "id": "a43",
      "category": "साई",
      "title": "आरती #43",
      "lyrics": "साई आरती #43 के पद..."
    },
    {
      "id": "a44",
      "category": "गायत्री",
      "title": "आरती #44",
      "lyrics": "गायत्री आरती #44 के पद..."
    },
    {
      "id": "a45",
      "category": "खाटू श्याम",
      "title": "आरती #45",
      "lyrics": "खाटू श्याम आरती #45 के पद..."
    },
    {
      "id": "a46",
      "category": "भैरव",
      "title": "आरती #46",
      "lyrics": "भैरव आरती #46 के पद..."
    },
    {
      "id": "a47",
      "category": "झूलेलाल",
      "title": "आरती #47",
      "lyrics": "झूलेलाल आरती #47 के पद..."
    },
    {
      "id": "a48",
      "category": "शिव",
      "title": "आरती #48",
      "lyrics": "शिव आरती #48 के पद..."
    },
    {
      "id": "a49",
      "category": "कृष्ण",
      "title": "आरती #49",
      "lyrics": "कृष्ण आरती #49 के पद..."
    },
    {
      "id": "a50",
      "category": "राम",
      "title": "आरती #50",
      "lyrics": "राम आरती #50 के पद..."
    },
    {
      "id": "a51",
      "category": "हनुमान",
      "title": "आरती #51",
      "lyrics": "हनुमान आरती #51 के पद..."
    },
    {
      "id": "a52",
      "category": "दुर्गा",
      "title": "आरती #52",
      "lyrics": "दुर्गा आरती #52 के पद..."
    },
    {
      "id": "a53",
      "category": "लक्ष्मी",
      "title": "आरती #53",
      "lyrics": "लक्ष्मी आरती #53 के पद..."
    },
    {
      "id": "a54",
      "category": "सरस्वती",
      "title": "आरती #54",
      "lyrics": "सरस्वती आरती #54 के पद..."
    },
    {
      "id": "a55",
      "category": "साई",
      "title": "आरती #55",
      "lyrics": "साई आरती #55 के पद..."
    },
    {
      "id": "a56",
      "category": "गायत्री",
      "title": "आरती #56",
      "lyrics": "गायत्री आरती #56 के पद..."
    },
    {
      "id": "a57",
      "category": "खाटू श्याम",
      "title": "आरती #57",
      "lyrics": "खाटू श्याम आरती #57 के पद..."
    },
    {
      "id": "a58",
      "category": "भैरव",
      "title": "आरती #58",
      "lyrics": "भैरव आरती #58 के पद..."
    },
    {
      "id": "a59",
      "category": "झूलेलाल",
      "title": "आरती #59",
      "lyrics": "झूलेलाल आरती #59 के पद..."
    },
    {
      "id": "a60",
      "category": "शिव",
      "title": "आरती #60",
      "lyrics": "शिव आरती #60 के पद..."
    }
  ],
  "bhajans": [
    {
      "id": "b1",
      "category": "राम",
      "title": "श्री रामचन्द्र कृपालु भज मन",
      "lyrics": "श्री रामचन्द्र कृपालु भज मन, हरण भव भय दारुणम्..."
    },
    {
      "id": "b2",
      "category": "राम",
      "title": "रघुपति राघव राजाराम",
      "lyrics": "रघुपति राघव राजाराम, पतित पावन सीताराम..."
    },
    {
      "id": "b3",
      "category": "कृष्ण",
      "title": "हरे कृष्ण हरे राम",
      "lyrics": "हरे कृष्ण हरे कृष्ण, कृष्ण कृष्ण हरे हरे..."
    },
    {
      "id": "b4",
      "category": "कृष्ण",
      "title": "जय जय राधा रमण हरि बोल",
      "lyrics": "जय जय राधा रमण हरि बोल..."
    },
    {
      "id": "b5",
      "category": "मीरा",
      "title": "मेरे तो गिरधर गोपाल",
      "lyrics": "मेरे तो गिरधर गोपाल, दूसरो न कोई..."
    },
    {
      "id": "b6",
      "category": "कबीर",
      "title": "मन लागो मेरो यार फकीरी में",
      "lyrics": "मन लागो मेरो यार फकीरी में..."
    },
    {
      "id": "b7",
      "category": "साईं",
      "title": "साईं राम साईं श्याम",
      "lyrics": "साईं राम साईं श्याम..."
    },
    {
      "id": "b8",
      "category": "कृष्ण",
      "title": "मधुराष्टकम्",
      "lyrics": "अधरं मधुरं, वदनं मधुरं..."
    },
    {
      "id": "b9",
      "category": "हनुमान",
      "title": "जय हनुमान भजन",
      "lyrics": "जय हनुमान, संकट मोचन..."
    },
    {
      "id": "b10",
      "category": "दुर्गा",
      "title": "अम्बे तू है जगदम्बे काली",
      "lyrics": "अम्बे तू है जगदम्बे काली..."
    },
    {
      "id": "b11",
      "category": "झूलेलाल",
      "title": "भजन #11",
      "lyrics": "झूलेलाल भजन #11 की पंक्तियाँ..."
    },
    {
      "id": "b12",
      "category": "शिव",
      "title": "भजन #12",
      "lyrics": "शिव भजन #12 की पंक्तियाँ..."
    },
    {
      "id": "b13",
      "category": "कृष्ण",
      "title": "भजन #13",
      "lyrics": "कृष्ण भजन #13 की पंक्तियाँ..."
    },
    {
      "id": "b14",
      "category": "राम",
      "title": "भजन #14",
      "lyrics": "राम भजन #14 की पंक्तियाँ..."
    },
    {
      "id": "b15",
      "category": "हनुमान",
      "title": "भजन #15",
      "lyrics": "हनुमान भजन #15 की पंक्तियाँ..."
    },
    {
      "id": "b16",
      "category": "दुर्गा",
      "title": "भजन #16",
      "lyrics": "दुर्गा भजन #16 की पंक्तियाँ..."
    },
    {
      "id": "b17",
      "category": "लक्ष्मी",
      "title": "भजन #17",
      "lyrics": "लक्ष्मी भजन #17 की पंक्तियाँ..."
    },
    {
      "id": "b18",
      "category": "सरस्वती",
      "title": "भजन #18",
      "lyrics": "सरस्वती भजन #18 की पंक्तियाँ..."
    },
    {
      "id": "b19",
      "category": "साई",
      "title": "भजन #19",
      "lyrics": "साई भजन #19 की पंक्तियाँ..."
    },
    {
      "id": "b20",
      "category": "गायत्री",
      "title": "भजन #20",
      "lyrics": "गायत्री भजन #20 की पंक्तियाँ..."
    },
    {
      "id": "b21",
      "category": "खाटू श्याम",
      "title": "भजन #21",
      "lyrics": "खाटू श्याम भजन #21 की पंक्तियाँ..."
    },
    {
      "id": "b22",
      "category": "भैरव",
      "title": "भजन #22",
      "lyrics": "भैरव भजन #22 की पंक्तियाँ..."
    },
    {
      "id": "b23",
      "category": "झूलेलाल",
      "title": "भजन #23",
      "lyrics": "झूलेलाल भजन #23 की पंक्तियाँ..."
    },
    {
      "id": "b24",
      "category": "शिव",
      "title": "भजन #24",
      "lyrics": "शिव भजन #24 की पंक्तियाँ..."
    },
    {
      "id": "b25",
      "category": "कृष्ण",
      "title": "भजन #25",
      "lyrics": "कृष्ण भजन #25 की पंक्तियाँ..."
    },
    {
      "id": "b26",
      "category": "राम",
      "title": "भजन #26",
      "lyrics": "राम भजन #26 की पंक्तियाँ..."
    },
    {
      "id": "b27",
      "category": "हनुमान",
      "title": "भजन #27",
      "lyrics": "हनुमान भजन #27 की पंक्तियाँ..."
    },
    {
      "id": "b28",
      "category": "दुर्गा",
      "title": "भजन #28",
      "lyrics": "दुर्गा भजन #28 की पंक्तियाँ..."
    },
    {
      "id": "b29",
      "category": "लक्ष्मी",
      "title": "भजन #29",
      "lyrics": "लक्ष्मी भजन #29 की पंक्तियाँ..."
    },
    {
      "id": "b30",
      "category": "सरस्वती",
      "title": "भजन #30",
      "lyrics": "सरस्वती भजन #30 की पंक्तियाँ..."
    },
    {
      "id": "b31",
      "category": "साई",
      "title": "भजन #31",
      "lyrics": "साई भजन #31 की पंक्तियाँ..."
    },
    {
      "id": "b32",
      "category": "गायत्री",
      "title": "भजन #32",
      "lyrics": "गायत्री भजन #32 की पंक्तियाँ..."
    },
    {
      "id": "b33",
      "category": "खाटू श्याम",
      "title": "भजन #33",
      "lyrics": "खाटू श्याम भजन #33 की पंक्तियाँ..."
    },
    {
      "id": "b34",
      "category": "भैरव",
      "title": "भजन #34",
      "lyrics": "भैरव भजन #34 की पंक्तियाँ..."
    },
    {
      "id": "b35",
      "category": "झूलेलाल",
      "title": "भजन #35",
      "lyrics": "झूलेलाल भजन #35 की पंक्तियाँ..."
    },
    {
      "id": "b36",
      "category": "शिव",
      "title": "भजन #36",
      "lyrics": "शिव भजन #36 की पंक्तियाँ..."
    },
    {
      "id": "b37",
      "category": "कृष्ण",
      "title": "भजन #37",
      "lyrics": "कृष्ण भजन #37 की पंक्तियाँ..."
    },
    {
      "id": "b38",
      "category": "राम",
      "title": "भजन #38",
      "lyrics": "राम भजन #38 की पंक्तियाँ..."
    },
    {
      "id": "b39",
      "category": "हनुमान",
      "title": "भजन #39",
      "lyrics": "हनुमान भजन #39 की पंक्तियाँ..."
    },
    {
      "id": "b40",
      "category": "दुर्गा",
      "title": "भजन #40",
      "lyrics": "दुर्गा भजन #40 की पंक्तियाँ..."
    },
    {
      "id": "b41",
      "category": "लक्ष्मी",
      "title": "भजन #41",
      "lyrics": "लक्ष्मी भजन #41 की पंक्तियाँ..."
    },
    {
      "id": "b42",
      "category": "सरस्वती",
      "title": "भजन #42",
      "lyrics": "सरस्वती भजन #42 की पंक्तियाँ..."
    },
    {
      "id": "b43",
      "category": "साई",
      "title": "भजन #43",
      "lyrics": "साई भजन #43 की पंक्तियाँ..."
    },
    {
      "id": "b44",
      "category": "गायत्री",
      "title": "भजन #44",
      "lyrics": "गायत्री भजन #44 की पंक्तियाँ..."
    },
    {
      "id": "b45",
      "category": "खाटू श्याम",
      "title": "भजन #45",
      "lyrics": "खाटू श्याम भजन #45 की पंक्तियाँ..."
    },
    {
      "id": "b46",
      "category": "भैरव",
      "title": "भजन #46",
      "lyrics": "भैरव भजन #46 की पंक्तियाँ..."
    },
    {
      "id": "b47",
      "category": "झूलेलाल",
      "title": "भजन #47",
      "lyrics": "झूलेलाल भजन #47 की पंक्तियाँ..."
    },
    {
      "id": "b48",
      "category": "शिव",
      "title": "भजन #48",
      "lyrics": "शिव भजन #48 की पंक्तियाँ..."
    },
    {
      "id": "b49",
      "category": "कृष्ण",
      "title": "भजन #49",
      "lyrics": "कृष्ण भजन #49 की पंक्तियाँ..."
    },
    {
      "id": "b50",
      "category": "राम",
      "title": "भजन #50",
      "lyrics": "राम भजन #50 की पंक्तियाँ..."
    },
    {
      "id": "b51",
      "category": "हनुमान",
      "title": "भजन #51",
      "lyrics": "हनुमान भजन #51 की पंक्तियाँ..."
    },
    {
      "id": "b52",
      "category": "दुर्गा",
      "title": "भजन #52",
      "lyrics": "दुर्गा भजन #52 की पंक्तियाँ..."
    },
    {
      "id": "b53",
      "category": "लक्ष्मी",
      "title": "भजन #53",
      "lyrics": "लक्ष्मी भजन #53 की पंक्तियाँ..."
    },
    {
      "id": "b54",
      "category": "सरस्वती",
      "title": "भजन #54",
      "lyrics": "सरस्वती भजन #54 की पंक्तियाँ..."
    },
    {
      "id": "b55",
      "category": "साई",
      "title": "भजन #55",
      "lyrics": "साई भजन #55 की पंक्तियाँ..."
    },
    {
      "id": "b56",
      "category": "गायत्री",
      "title": "भजन #56",
      "lyrics": "गायत्री भजन #56 की पंक्तियाँ..."
    },
    {
      "id": "b57",
      "category": "खाटू श्याम",
      "title": "भजन #57",
      "lyrics": "खाटू श्याम भजन #57 की पंक्तियाँ..."
    },
    {
      "id": "b58",
      "category": "भैरव",
      "title": "भजन #58",
      "lyrics": "भैरव भजन #58 की पंक्तियाँ..."
    },
    {
      "id": "b59",
      "category": "झूलेलाल",
      "title": "भजन #59",
      "lyrics": "झूलेलाल भजन #59 की पंक्तियाँ..."
    },
    {
      "id": "b60",
      "category": "शिव",
      "title": "भजन #60",
      "lyrics": "शिव भजन #60 की पंक्तियाँ..."
    }
  ]
}